{
  "testName": "Feedrate Performance Comparison",
  "timestamp": "2026-02-20T15:38:44.036Z",
  "firstJob": {
    "initialFeedrate": "100%",
    "finalFeedrate": "50%",
    "timeTaken": "00:00:29",
    "timeInSeconds": 29
  },
  "secondJob": {
    "initialFeedrate": "100%",
    "finalFeedrate": "150%",
    "timeTaken": "00:00:20",
    "timeInSeconds": 20
  },
  "comparison": {
    "timeDifferenceSeconds": 9,
    "timeDifference": "9s",
    "percentageDifference": "31.03%",
    "fasterJob": "Second Job (Higher Feedrate)",
    "conclusion": "Higher feedrate resulted in faster completion as expected"
  }
}